Workbook

Sheet Simulador FIIs
B1: SIMULADOR DE INVESTIMENTOS EM FIIs - PRO
B2: Planejamento Financeiro, Reajuste de Inflacao e Alocacao Inteligente por Perfil
B4: Aporte Mensal Inicial | D4: Patrimonio Estimado (5 Anos) | F4: Lucro em Juros Compostos | H4: Renda Mensal (Dividendos)
B5: =D14 -> 200 | D5: =G26 -> 16755.383 | F5: =H26 -> 4755.3828 | H5: =I26 -> 100.5323
B8: [1] PARAMETROS DA SIMULACAO DE INVESTIMENTO
B10: Salario Mensal do Investidor | D10: 2000
B11: Percentual Sugerido para Investir | D11: 0.3
B12: Sugestao de Aporte (30% do Salario) | D12: =D10*D11 -> 600
B14: Aporte Mensal Praticado (Editable) | D14: 200
B15: Periodo Base da Simulacao (Anos) | D15: 5
B16: Taxa de Inflacao Anual Estimada (IPCA) | D16: 0.045
B17: Taxa de Rendimento Mensal dos FIIs | D17: 0.01079
B18: Dividend Yield Mensal Medio (DY) | D18: 0.006
B20: [2] PROJECAO TEMPORAL: NOMINAL vs. REAJUSTE DE INFLACAO E JUROS COMPOSTOS
B22: Prazo (Anos) | C22: Meses | D22: Aporte Reajustado (Fim) | E22: Total Investido (Sem Inflacao) | F22: Total Investido (Com Inflacao) | G22: Patrimonio Acumulado (Nominal) | H22: Lucro dos Juros (R$) | I22: Dividendo Mensal (R$) | J22: Cotas Novas/Mes (R$ 100)
B25: 2 | C25: =B25*12 -> 24 | D25: =D14*(1+$D$16)^B25 -> 218.405 | E25: =D14*C25 -> 4800 | F25: =D14*12*((1+$D$16)^B25 - 1)/$D$16 -> 4908 | G25: =FV($D$17, C25, -D14) -> 5445.5255 | H25: =G25-E25 -> 645.52546 | I25: =G25*$D$18 -> 32.673153 | J25: =INT(I25/100) -> 0
B26: 5 | C26: =B26*12 -> 60 | D26: =D14*(1+$D$16)^B26 -> 249.23639 | E26: =D14*C26 -> 12000 | F26: =D14*12*((1+$D$16)^B26 - 1)/$D$16 -> 13129.703 | G26: =FV($D$17, C26, -D14) -> 16755.383 | H26: =G26-E26 -> 4755.3828 | I26: =G26*$D$18 -> 100.5323 | J26: =INT(I26/100) -> 1
B27: 10 | C27: =B27*12 -> 120 | D27: =D14*(1+$D$16)^B27 -> 310.59388 | E27: =D14*C27 -> 24000 | F27: =D14*12*((1+$D$16)^B27 - 1)/$D$16 -> 29491.702 | G27: =FV($D$17, C27, -D14) -> 48656.843 | H27: =G27-E27 -> 24656.843 | I27: =G27*$D$18 -> 291.94106 | J27: =INT(I27/100) -> 2
B28: 20 | C28: =B28*12 -> 240 | D28: =D14*(1+$D$16)^B28 -> 482.3428 | E28: =D14*C28 -> 48000 | F28: =D14*12*((1+$D$16)^B28 - 1)/$D$16 -> 75291.415 | G28: =FV($D$17, C28, -D14) -> 225039.68 | H28: =G28-E28 -> 177039.68 | I28: =G28*$D$18 -> 1350.2381 | J28: =INT(I28/100) -> 13
B29: 30 | C29: =B29*12 -> 360 | D29: =D14*(1+$D$16)^B29 -> 749.06363 | E29: =D14*C29 -> 72000 | F29: =D14*12*((1+$D$16)^B29 - 1)/$D$16 -> 146416.97 | G29: =FV($D$17, C29, -D14) -> 864433.93 | H29: =G29-E29 -> 792433.93 | I29: =G29*$D$18 -> 5186.6036 | J29: =INT(I29/100) -> 51
B32: [3] ESTRATEGIA DE ALOCACAO POR PERFIL DE INVESTIDOR
B34: Perfil Selecionado | C34: Moderado
B35: Valor a Ser Investido / Mes | C35: =D14 -> 200
B37: Tipo de FII | C37: Descricao do Segmento | G37: % Sugerido | H37: Valor Alocado (R$)
B38: PAPEL | C38: Certificados de Recebiveis Imobiliarios (CRI) | G38: =IFERROR(VLOOKUP($C$34&"-"&B38, Matriz_Alocacao!$A:$D, 4, FALSE), 0) -> 0.32 | H38: =G38*$C$35 -> 64
B39: TIJOLO | C39: Shopping Centers, Galpoes Logisticos, Lajes Corporativas | G39: =IFERROR(VLOOKUP($C$34&"-"&B39, Matriz_Alocacao!$A:$D, 4, FALSE), 0) -> 0.35 | H39: =G39*$C$35 -> 70
B40: HIBRIDOS | C40: Mistura de Tijolo, Papel e Outros Fundos | G40: =IFERROR(VLOOKUP($C$34&"-"&B40, Matriz_Alocacao!$A:$D, 4, FALSE), 0) -> 0.08 | H40: =G40*$C$35 -> 16
B41: FOFs | C41: Fundos de Fundos Imobiliarios | G41: =IFERROR(VLOOKUP($C$34&"-"&B41, Matriz_Alocacao!$A:$D, 4, FALSE), 0) -> 0.05 | H41: =G41*$C$35 -> 10
B42: DESENVOLVIMENTO | C42: Projetos de Construcao e Incorporacao | G42: =IFERROR(VLOOKUP($C$34&"-"&B42, Matriz_Alocacao!$A:$D, 4, FALSE), 0) -> 0.1 | H42: =G42*$C$35 -> 20
B43: HOTELARIAS | C43: Empreendimentos Hoteleiros e Flats | G43: =IFERROR(VLOOKUP($C$34&"-"&B43, Matriz_Alocacao!$A:$D, 4, FALSE), 0) -> 0.1 | H43: =G43*$C$35 -> 20
B44: TOTAL ALOCADO | G44: =SUM(G38:G43) -> 1 | H44: =SUM(H38:H43) -> 200

Sheet Matriz_Alocacao
A2: CHAVE | B2: PERFIL | C2: TIPO DE FII | D2: % RECOMENDADO
A3: Conservador-PAPEL | B3: Conservador | C3: PAPEL | D3: 0.3
A4: Conservador-TIJOLO | B4: Conservador | C4: TIJOLO | D4: 0.5
A5: Conservador-HIBRIDOS | B5: Conservador | C5: HIBRIDOS | D5: 0.1
A6: Conservador-FOFs | B6: Conservador | C6: FOFs | D6: 0.1
A7: Conservador-DESENVOLVIMENTO | B7: Conservador | C7: DESENVOLVIMENTO | D7: 0
A8: Conservador-HOTELARIAS | B8: Conservador | C8: HOTELARIAS | D8: 0
A9: Moderado-PAPEL | B9: Moderado | C9: PAPEL | D9: 0.32
A10: Moderado-TIJOLO | B10: Moderado | C10: TIJOLO | D10: 0.35
A11: Moderado-HIBRIDOS | B11: Moderado | C11: HIBRIDOS | D11: 0.08
A12: Moderado-FOFs | B12: Moderado | C12: FOFs | D12: 0.05
A13: Moderado-DESENVOLVIMENTO | B13: Moderado | C13: DESENVOLVIMENTO | D13: 0.1
A14: Moderado-HOTELARIAS | B14: Moderado | C14: HOTELARIAS | D14: 0.1
... A20: Agressivo-HOTELARIAS | B20: Agressivo | C20: HOTELARIAS | D20: 0.1
